canvas_api_client/__init__.py
canvas_api_client/errors.py
canvas_api_client/interface.py
canvas_api_client/types.py
canvas_api_client/v1_client.py
canvas_api_client-0.2.11.dist-info/METADATA
canvas_api_client-0.2.11.dist-info/RECORD
canvas_api_client-0.2.11.dist-info/WHEEL
canvas_api_client-0.2.11.dist-info/dependency_links.txt
canvas_api_client-0.2.11.dist-info/top_level.txt
