Metadata-Version: 2.1
Name: canvas-api-client
Version: 0.2.11
Summary: This is a library for making requests to a Canvas LMS API.
Home-page: https://github.com/lcary/canvas-lms-tools
Author: Luc Cary
Author-email: luc.cary@gmail.com
License: Apache
Download-URL: https://github.com/lcary/canvas-lms-tools/archive/0.2.11
Platform: UNKNOWN
Classifier: Development Status :: 3 - Alpha
Classifier: Intended Audience :: Developers
Classifier: Programming Language :: Python :: 3
Requires-Dist: requests (==2.18.1)
